flake8_tuple.py
flake8_tuple-0.4.1.dist-info/AUTHORS.rst
flake8_tuple-0.4.1.dist-info/LICENSE
flake8_tuple-0.4.1.dist-info/METADATA
flake8_tuple-0.4.1.dist-info/WHEEL
flake8_tuple-0.4.1.dist-info/entry_points.txt
flake8_tuple-0.4.1.dist-info/top_level.txt
flake8_tuple-0.4.1.dist-info/RECORD
