Metadata-Version: 1.1
Name: flake8_tuple
Version: 0.4.1
Summary: Check code for 1 element tuple.
Home-page: https://github.com/ar4s/flake8_tuple
Author: Arkadiusz Adamski
Author-email: arkadiusz.adamski@gmail.com
License: BSD
Keywords: flake8_tuple
Platform: UNKNOWN
Classifier: Intended Audience :: Developers
Classifier: License :: OSI Approved :: BSD License
Classifier: Natural Language :: English
Classifier: Programming Language :: Python :: 2.7
Classifier: Programming Language :: Python :: 3.4
Classifier: Programming Language :: Python :: 3.5
Classifier: Programming Language :: Python :: 3.6
Classifier: Programming Language :: Python :: 3.7
